<?xml version="1.0" encoding="UTF-8"?>
<gresources>
  <gresource prefix="/me/appadeia/Taigo">
    <file>window.ui</file>
    <file>status.ui</file>
    <file>food.ui</file>
    <file>debuglabel.ui</file>
    <file>debugwindow.ui</file>
    <file>game.ui</file>

    <file>css/app.css</file>

    <file>icons/scalable/actions/heart-filled-symbolic.svg</file>
    <file>icons/scalable/actions/restaurant-symbolic.svg</file>
    <file>icons/scalable/actions/folder-symbolic.svg</file>
    <file>icons/scalable/actions/gamepad-symbolic.svg</file>
    <file>icons/scalable/actions/arrow1-left-symbolic.svg</file>
    <file>icons/scalable/actions/arrow1-right-symbolic.svg</file>

    <file>images/bgs/home.svg</file>

    <file>images/taigochi/Taikocha/normal.svg</file>
    <file>images/taigochi/Taikoche/normal.svg</file>
    <file>images/taigochi/Taikochi/normal.svg</file>
    <file>images/taigochi/Molichi/normal.svg</file>

    <file>images/taigochi/Taikocha/blink.svg</file>
    <file>images/taigochi/Taikoche/blink.svg</file>
    <file>images/taigochi/Taikochi/blink.svg</file>
    <file>images/taigochi/Molichi/blink.svg</file>

    <file>images/animations/meal/idle.svg</file>
    <file>images/animations/treat/idle.svg</file>
    <file>images/animations/meal/eat-1.svg</file>
    <file>images/animations/treat/eat-1.svg</file>
    <file>images/animations/meal/eat-2.svg</file>
    <file>images/animations/treat/eat-2.svg</file>
    <file>images/animations/meal/eat-3.svg</file>
    <file>images/animations/treat/eat-3.svg</file>
    <file>images/animations/meal/eat-4.svg</file>
    <file>images/animations/treat/eat-4.svg</file>
    <file>images/animations/meal/blank.svg</file>
    <file>images/animations/treat/blank.svg</file>
  </gresource>
</gresources>
